setup.py
Guajiro.egg-info/PKG-INFO
Guajiro.egg-info/SOURCES.txt
Guajiro.egg-info/dependency_links.txt
Guajiro.egg-info/entry_points.txt
Guajiro.egg-info/not-zip-safe
Guajiro.egg-info/requires.txt
Guajiro.egg-info/top_level.txt
guajiro/__init__.py
guajiro/cmdline.py
guajiro/commands/__init__.py
guajiro/commands/seed.py
guajiro/core/__init__.py
guajiro/core/app.py
guajiro/core/decorators.py
guajiro/core/exceptions.py
guajiro/core/helpers.py
guajiro/core/inspector.py
guajiro/core/response_types.py
guajiro/core/router.py
guajiro/core/views.py
guajiro/core/middlewares/__init__.py
guajiro/core/middlewares/base.py
guajiro/exceptions/__init__.py